CHANGES.rst
DESCRIPTION.rst
LICENSE
MANIFEST.in
README.md
setup.py
src/idc/redis/__init__.py
src/idc/redis/class_lister.py
src/idc/redis/core.py
src/idc/redis/filter/__init__.py
src/idc/redis/filter/_redis_filter.py
src/idc/redis/filter/_redis_predict_dp.py
src/idc/redis/filter/_redis_predict_ic.py
src/idc/redis/filter/_redis_predict_is.py
src/idc/redis/filter/_redis_predict_od.py
src/idc/redis/filter/_redis_pubsub_filter.py
src/idc/redis/reader/__init__.py
src/idc/redis/reader/_redis_image_listen.py
src/idc/redis/reader/_redis_listener.py
src/idc/redis/reader/_redis_reader.py
src/idc/redis/writer/__init__.py
src/idc/redis/writer/_redis_broadcaster.py
src/idc/redis/writer/_redis_data_broadcast.py
src/idc/redis/writer/_redis_writer.py
src/image_dataset_converter_redis.egg-info/PKG-INFO
src/image_dataset_converter_redis.egg-info/SOURCES.txt
src/image_dataset_converter_redis.egg-info/dependency_links.txt
src/image_dataset_converter_redis.egg-info/entry_points.txt
src/image_dataset_converter_redis.egg-info/requires.txt
src/image_dataset_converter_redis.egg-info/top_level.txt